cmdlinetest1/__init__.py
cmdlinetest1/clirest_api.py
cmdlinetest1-1.0.0.dist-info/METADATA
cmdlinetest1-1.0.0.dist-info/WHEEL
cmdlinetest1-1.0.0.dist-info/entry_points.txt
cmdlinetest1-1.0.0.dist-info/top_level.txt
cmdlinetest1-1.0.0.dist-info/RECORD
