Metadata-Version: 2.1
Name: cmdlinetest1
Version: 1.0.0
Summary: Demo Package for CLI
Home-page: UNKNOWN
Author: Bhakti Jadhav
Author-email: bhaktij910@gmail.com
License: UNKNOWN
Platform: UNKNOWN
Classifier: Programming Language :: Python :: 3
Classifier: Operating System :: OS Independent
